SDAdice
