Metadata-Version: 2.1
Name: SDAdice
Version: 1.0.1
Summary: A package that plays dice game
Author: Guido Xhindoli
Author-email: <mail@gmail.com>
Keywords: SDAdice,pythonsdaal,playdice,sda,SDA
Classifier: Development Status :: 1 - Planning
Classifier: Intended Audience :: Developers
Classifier: Programming Language :: Python :: 3
Classifier: Operating System :: Unix
Classifier: Operating System :: MacOS :: MacOS X
Classifier: Operating System :: Microsoft :: Windows
